LICENSE
README.md
setup.py
codeboxcli/__init__.py
codeboxcli/__main__.py
codeboxcli.egg-info/PKG-INFO
codeboxcli.egg-info/SOURCES.txt
codeboxcli.egg-info/dependency_links.txt
codeboxcli.egg-info/entry_points.txt
codeboxcli.egg-info/requires.txt
codeboxcli.egg-info/top_level.txt
codeboxcli/commands/add.py
codeboxcli/commands/delete.py
codeboxcli/commands/edit.py
codeboxcli/commands/list.py
codeboxcli/commands/share.py
codeboxcli/locales/ca.py
codeboxcli/locales/en.py
codeboxcli/locales/es.py
codeboxcli/models/models.py
codeboxcli/utils/default_editor.py
codeboxcli/utils/messages.py
codeboxcli/utils/pastebin.py