Metadata-Version: 2.1
Name: codeboxcli
Version: 23.10.4
Summary: CLI for Saving and Sharing Code Snippets
Author: Marc Orfila Carreras
License-File: LICENSE
